{"mid": [{"value": 32882}], "uuid": [{"value": "ddf3cafa-dbf6-4deb-8e34-26a7f83f39b0"}], "vid": [{"value": 32882}], "langcode": [{"value": "en"}], "bundle": [{"target_id": "image", "target_type": "media_type", "target_uuid": "0e176bd2-57a7-43af-b904-2275b557167d"}], "revision_created": [{"value": "2022-03-14T21:18:32+00:00", "format": "Y-m-d\\TH:i:sP"}], "revision_user": [], "revision_log_message": [], "status": [{"value": true}], "uid": [{"target_id": 534, "target_type": "user", "target_uuid": "dfa33910-e475-482d-9fb2-7c268bc2ee7b", "url": "/user/534"}], "name": [{"value": "6169-Service File.jpg"}], "thumbnail": [{"target_id": 33429, "alt": "6169-Service File.jpg", "title": null, "width": 4174, "height": 5861, "target_type": "file", "target_uuid": "2a574a3d-4e79-4f83-a9b7-24ff9afebb0d", "url": "http://digital.library.jhu.edu/system/files/2022-03/6169-Service%20File.jpg"}], "created": [{"value": "2022-03-14T21:18:32+00:00", "format": "Y-m-d\\TH:i:sP"}], "changed": [{"value": "2022-03-14T21:18:32+00:00", "format": "Y-m-d\\TH:i:sP"}], "default_langcode": [{"value": true}], "revision_translation_affected": [{"value": true}], "content_translation_source": [{"value": "und"}], "content_translation_outdated": [{"value": false}], "field_access_terms": [], "field_file_size": [{"value": 743546}], "field_height": [{"value": 5861}], "field_media_image": [{"target_id": 33429, "alt": "6169-Service File.jpg", "title": null, "width": 4174, "height": 5861, "target_type": "file", "target_uuid": "2a574a3d-4e79-4f83-a9b7-24ff9afebb0d", "url": "http://digital.library.jhu.edu/system/files/2022-03/6169-Service%20File.jpg"}], "field_media_of": [{"target_id": 6169, "target_type": "node", "target_uuid": "08e4ef0d-bdc5-43c7-85f8-1d226b7b01e9", "url": "/node/6169"}], "field_media_use": [{"target_id": 19, "target_type": "taxonomy_term", "target_uuid": "42ded87c-0c70-44c5-bbdf-89bc69b8f12e", "url": "/taxonomy/term/19"}], "field_mime_type": [{"value": "image/jpeg"}], "field_original_name": [], "field_restricted_access": [{"value": false}], "field_unique_id": [{"value": "8d41b8c1-60b3-4512-98a5-52c3016c7cc2"}], "field_width": [{"value": 4174}]}