{"mid": [{"value": 16737}], "uuid": [{"value": "79988d5d-2cac-4387-946b-7e68787d71f5"}], "vid": [{"value": 16737}], "langcode": [{"value": "en"}], "bundle": [{"target_id": "image", "target_type": "media_type", "target_uuid": "0e176bd2-57a7-43af-b904-2275b557167d"}], "revision_created": [{"value": "2022-03-14T15:22:46+00:00", "format": "Y-m-d\\TH:i:sP"}], "revision_user": [], "revision_log_message": [], "status": [{"value": true}], "uid": [{"target_id": 534, "target_type": "user", "target_uuid": "dfa33910-e475-482d-9fb2-7c268bc2ee7b", "url": "/user/534"}], "name": [{"value": "9592-Service File.jpg"}], "thumbnail": [{"target_id": 17280, "alt": "9592-Service File.jpg", "title": null, "width": 2691, "height": 3938, "target_type": "file", "target_uuid": "6089b3cd-6513-47a2-9197-53c332d06100", "url": "http://digital.library.jhu.edu/system/files/2022-03/9592-Service%20File.jpg"}], "created": [{"value": "2022-03-14T15:22:46+00:00", "format": "Y-m-d\\TH:i:sP"}], "changed": [{"value": "2022-03-14T15:22:46+00:00", "format": "Y-m-d\\TH:i:sP"}], "default_langcode": [{"value": true}], "revision_translation_affected": [{"value": true}], "content_translation_source": [{"value": "und"}], "content_translation_outdated": [{"value": false}], "field_access_terms": [], "field_file_size": [{"value": 650279}], "field_height": [{"value": 3938}], "field_media_image": [{"target_id": 17280, "alt": "9592-Service File.jpg", "title": null, "width": 2691, "height": 3938, "target_type": "file", "target_uuid": "6089b3cd-6513-47a2-9197-53c332d06100", "url": "http://digital.library.jhu.edu/system/files/2022-03/9592-Service%20File.jpg"}], "field_media_of": [{"target_id": 9592, "target_type": "node", "target_uuid": "3164d5ff-f6df-4a5c-a49b-d0821602cf2d", "url": "/node/9592"}], "field_media_use": [{"target_id": 19, "target_type": "taxonomy_term", "target_uuid": "42ded87c-0c70-44c5-bbdf-89bc69b8f12e", "url": "/taxonomy/term/19"}], "field_mime_type": [{"value": "image/jpeg"}], "field_original_name": [], "field_restricted_access": [{"value": false}], "field_unique_id": [{"value": "f4e0750b-8093-4907-90a0-73d3e05393a3"}], "field_width": [{"value": 2691}]}