{"mid": [{"value": 27248}], "uuid": [{"value": "b6e8e3f5-8089-4ba4-8ee6-6e9330a4ceb6"}], "vid": [{"value": 27248}], "langcode": [{"value": "en"}], "bundle": [{"target_id": "image", "target_type": "media_type", "target_uuid": "0e176bd2-57a7-43af-b904-2275b557167d"}], "revision_created": [{"value": "2022-03-14T19:17:58+00:00", "format": "Y-m-d\\TH:i:sP"}], "revision_user": [], "revision_log_message": [], "status": [{"value": true}], "uid": [{"target_id": 534, "target_type": "user", "target_uuid": "dfa33910-e475-482d-9fb2-7c268bc2ee7b", "url": "/user/534"}], "name": [{"value": "11629-Service File.jpg"}], "thumbnail": [{"target_id": 27795, "alt": "11629-Service File.jpg", "title": null, "width": 5798, "height": 4151, "target_type": "file", "target_uuid": "25d4b8cb-cc12-487a-a0e5-27b1ea8b6f23", "url": "http://digital.library.jhu.edu/system/files/2022-03/11629-Service%20File.jpg"}], "created": [{"value": "2022-03-14T19:17:58+00:00", "format": "Y-m-d\\TH:i:sP"}], "changed": [{"value": "2022-03-14T19:17:58+00:00", "format": "Y-m-d\\TH:i:sP"}], "default_langcode": [{"value": true}], "revision_translation_affected": [{"value": true}], "content_translation_source": [{"value": "und"}], "content_translation_outdated": [{"value": false}], "field_access_terms": [], "field_file_size": [{"value": 2020977}], "field_height": [{"value": 4151}], "field_media_image": [{"target_id": 27795, "alt": "11629-Service File.jpg", "title": null, "width": 5798, "height": 4151, "target_type": "file", "target_uuid": "25d4b8cb-cc12-487a-a0e5-27b1ea8b6f23", "url": "http://digital.library.jhu.edu/system/files/2022-03/11629-Service%20File.jpg"}], "field_media_of": [{"target_id": 11629, "target_type": "node", "target_uuid": "13d5b1c8-c26c-4d6d-a303-9f7ead64ae0b", "url": "/node/11629"}], "field_media_use": [{"target_id": 19, "target_type": "taxonomy_term", "target_uuid": "42ded87c-0c70-44c5-bbdf-89bc69b8f12e", "url": "/taxonomy/term/19"}], "field_mime_type": [{"value": "image/jpeg"}], "field_original_name": [], "field_restricted_access": [{"value": false}], "field_unique_id": [{"value": "ec6fba02-bec7-40e8-ad00-b142f9639fb9"}], "field_width": [{"value": 5798}]}