{"mid": [{"value": 34882}], "uuid": [{"value": "7c19096a-7d44-4961-aae3-d4171ad5b9db"}], "vid": [{"value": 34882}], "langcode": [{"value": "en"}], "bundle": [{"target_id": "image", "target_type": "media_type", "target_uuid": "0e176bd2-57a7-43af-b904-2275b557167d"}], "revision_created": [{"value": "2022-03-14T22:46:47+00:00", "format": "Y-m-d\\TH:i:sP"}], "revision_user": [], "revision_log_message": [], "status": [{"value": true}], "uid": [{"target_id": 534, "target_type": "user", "target_uuid": "dfa33910-e475-482d-9fb2-7c268bc2ee7b", "url": "/user/534"}], "name": [{"value": "3550-Service File.jpg"}], "thumbnail": [{"target_id": 35429, "alt": "3550-Service File.jpg", "title": null, "width": 8127, "height": 6437, "target_type": "file", "target_uuid": "dd82b34d-f0d0-4cc0-9ffc-69397ad0c180", "url": "http://digital.library.jhu.edu/system/files/2022-03/3550-Service%20File.jpg"}], "created": [{"value": "2022-03-14T22:46:47+00:00", "format": "Y-m-d\\TH:i:sP"}], "changed": [{"value": "2022-03-14T22:46:47+00:00", "format": "Y-m-d\\TH:i:sP"}], "default_langcode": [{"value": true}], "revision_translation_affected": [{"value": true}], "content_translation_source": [{"value": "und"}], "content_translation_outdated": [{"value": false}], "field_access_terms": [], "field_file_size": [{"value": 1389987}], "field_height": [{"value": 6437}], "field_media_image": [{"target_id": 35429, "alt": "3550-Service File.jpg", "title": null, "width": 8127, "height": 6437, "target_type": "file", "target_uuid": "dd82b34d-f0d0-4cc0-9ffc-69397ad0c180", "url": "http://digital.library.jhu.edu/system/files/2022-03/3550-Service%20File.jpg"}], "field_media_of": [{"target_id": 3550, "target_type": "node", "target_uuid": "0c919f40-84f5-461e-8890-d873ce820a55", "url": "/node/3550"}], "field_media_use": [{"target_id": 19, "target_type": "taxonomy_term", "target_uuid": "42ded87c-0c70-44c5-bbdf-89bc69b8f12e", "url": "/taxonomy/term/19"}], "field_mime_type": [{"value": "image/jpeg"}], "field_original_name": [], "field_restricted_access": [{"value": false}], "field_unique_id": [{"value": "71e63631-4775-4e99-a007-3490fc9fc06b"}], "field_width": [{"value": 8127}]}