{"mid": [{"value": 3345}], "uuid": [{"value": "91a1eca6-cf86-4751-825e-1839feabcedd"}], "vid": [{"value": 3345}], "langcode": [{"value": "en"}], "bundle": [{"target_id": "image", "target_type": "media_type", "target_uuid": "0e176bd2-57a7-43af-b904-2275b557167d"}], "revision_created": [{"value": "2022-03-11T20:21:14+00:00", "format": "Y-m-d\\TH:i:sP"}], "revision_user": [], "revision_log_message": [], "status": [{"value": true}], "uid": [{"target_id": 534, "target_type": "user", "target_uuid": "dfa33910-e475-482d-9fb2-7c268bc2ee7b", "url": "/user/534"}], "name": [{"value": "781-Service File.jpg"}], "thumbnail": [{"target_id": 3884, "alt": "781-Service File.jpg", "title": null, "width": 5323, "height": 8041, "target_type": "file", "target_uuid": "ee10f15c-45ca-4ff3-9fd2-ac1ca449c70d", "url": "http://digital.library.jhu.edu/system/files/2022-03/781-Service%20File.jpg"}], "created": [{"value": "2022-03-11T20:21:14+00:00", "format": "Y-m-d\\TH:i:sP"}], "changed": [{"value": "2022-03-11T20:21:14+00:00", "format": "Y-m-d\\TH:i:sP"}], "default_langcode": [{"value": true}], "revision_translation_affected": [{"value": true}], "content_translation_source": [{"value": "und"}], "content_translation_outdated": [{"value": false}], "field_access_terms": [], "field_file_size": [{"value": 2463618}], "field_height": [{"value": 8041}], "field_media_image": [{"target_id": 3884, "alt": "781-Service File.jpg", "title": null, "width": 5323, "height": 8041, "target_type": "file", "target_uuid": "ee10f15c-45ca-4ff3-9fd2-ac1ca449c70d", "url": "http://digital.library.jhu.edu/system/files/2022-03/781-Service%20File.jpg"}], "field_media_of": [{"target_id": 781, "target_type": "node", "target_uuid": "294f5ce5-2919-4a98-936b-05a7099e07c7", "url": "/node/781"}], "field_media_use": [{"target_id": 19, "target_type": "taxonomy_term", "target_uuid": "42ded87c-0c70-44c5-bbdf-89bc69b8f12e", "url": "/taxonomy/term/19"}], "field_mime_type": [{"value": "image/jpeg"}], "field_original_name": [], "field_restricted_access": [{"value": false}], "field_unique_id": [{"value": "0acb966f-d689-4733-88aa-c1a71bf426e8"}], "field_width": [{"value": 5323}]}