{"mid": [{"value": 6334}], "uuid": [{"value": "f3b267bd-f1dd-4c6d-9b7f-475a435c50a8"}], "vid": [{"value": 6334}], "langcode": [{"value": "en"}], "bundle": [{"target_id": "image", "target_type": "media_type", "target_uuid": "0e176bd2-57a7-43af-b904-2275b557167d"}], "revision_created": [{"value": "2022-03-11T21:18:23+00:00", "format": "Y-m-d\\TH:i:sP"}], "revision_user": [], "revision_log_message": [], "status": [{"value": true}], "uid": [{"target_id": 534, "target_type": "user", "target_uuid": "dfa33910-e475-482d-9fb2-7c268bc2ee7b", "url": "/user/534"}], "name": [{"value": "8305-Service File.jpg"}], "thumbnail": [{"target_id": 6874, "alt": "8305-Service File.jpg", "title": null, "width": 6304, "height": 7840, "target_type": "file", "target_uuid": "160b33cd-30d5-465b-9263-90ccc46b7721", "url": "http://digital.library.jhu.edu/system/files/2022-03/8305-Service%20File.jpg"}], "created": [{"value": "2022-03-11T21:18:23+00:00", "format": "Y-m-d\\TH:i:sP"}], "changed": [{"value": "2022-03-11T21:18:23+00:00", "format": "Y-m-d\\TH:i:sP"}], "default_langcode": [{"value": true}], "revision_translation_affected": [{"value": true}], "content_translation_source": [{"value": "und"}], "content_translation_outdated": [{"value": false}], "field_access_terms": [], "field_file_size": [{"value": 906499}], "field_height": [{"value": 7840}], "field_media_image": [{"target_id": 6874, "alt": "8305-Service File.jpg", "title": null, "width": 6304, "height": 7840, "target_type": "file", "target_uuid": "160b33cd-30d5-465b-9263-90ccc46b7721", "url": "http://digital.library.jhu.edu/system/files/2022-03/8305-Service%20File.jpg"}], "field_media_of": [{"target_id": 8305, "target_type": "node", "target_uuid": "f3e71bb9-0e0b-48ee-8259-2bf973e6bbc0", "url": "/node/8305"}], "field_media_use": [{"target_id": 19, "target_type": "taxonomy_term", "target_uuid": "42ded87c-0c70-44c5-bbdf-89bc69b8f12e", "url": "/taxonomy/term/19"}], "field_mime_type": [{"value": "image/jpeg"}], "field_original_name": [], "field_restricted_access": [{"value": false}], "field_unique_id": [{"value": "8537bf9c-e476-44e3-b4fd-056f8554e030"}], "field_width": [{"value": 6304}]}