{"mid": [{"value": 12753}], "uuid": [{"value": "c66b6563-eee5-48e2-907d-4dd06d266460"}], "vid": [{"value": 12753}], "langcode": [{"value": "en"}], "bundle": [{"target_id": "image", "target_type": "media_type", "target_uuid": "0e176bd2-57a7-43af-b904-2275b557167d"}], "revision_created": [{"value": "2022-03-14T13:55:06+00:00", "format": "Y-m-d\\TH:i:sP"}], "revision_user": [], "revision_log_message": [], "status": [{"value": true}], "uid": [{"target_id": 534, "target_type": "user", "target_uuid": "dfa33910-e475-482d-9fb2-7c268bc2ee7b", "url": "/user/534"}], "name": [{"value": "2833-Thumbnail Image.jpg"}], "thumbnail": [{"target_id": 13294, "alt": "2833-Thumbnail Image.jpg", "title": null, "width": 100, "height": 77, "target_type": "file", "target_uuid": "f9612c5b-f7bb-4cd7-ab01-e7cb730a5816", "url": "http://digital.library.jhu.edu/system/files/2022-03/2833-Thumbnail%20Image.jpg"}], "created": [{"value": "2022-03-14T13:55:06+00:00", "format": "Y-m-d\\TH:i:sP"}], "changed": [{"value": "2022-03-14T13:55:06+00:00", "format": "Y-m-d\\TH:i:sP"}], "default_langcode": [{"value": true}], "revision_translation_affected": [{"value": true}], "content_translation_source": [{"value": "und"}], "content_translation_outdated": [{"value": false}], "field_access_terms": [], "field_file_size": [{"value": 2205}], "field_height": [{"value": 77}], "field_media_image": [{"target_id": 13294, "alt": "2833-Thumbnail Image.jpg", "title": null, "width": 100, "height": 77, "target_type": "file", "target_uuid": "f9612c5b-f7bb-4cd7-ab01-e7cb730a5816", "url": "http://digital.library.jhu.edu/system/files/2022-03/2833-Thumbnail%20Image.jpg"}], "field_media_of": [{"target_id": 2833, "target_type": "node", "target_uuid": "69c81e03-f48e-4ec5-8ebb-d8d54107b138", "url": "/node/2833"}], "field_media_use": [{"target_id": 20, "target_type": "taxonomy_term", "target_uuid": "c0cb1a8e-e8ee-4c02-924f-3a5a6930b997", "url": "/taxonomy/term/20"}], "field_mime_type": [{"value": "image/jpeg"}], "field_original_name": [], "field_restricted_access": [{"value": false}], "field_unique_id": [{"value": "e95149fb-588d-4227-adec-2dcc23626ebe"}], "field_width": [{"value": 100}]}